<?xml version="1.0" encoding="UTF-8" ?>
<JavaBean xmlns="http://xmlns.oracle.com/adfm/beanmodel" version="11.1.1.60.13"
          id="tLeaveRequest" Package="LeaveFormProject_LeaveRequest"
          BeanClass="LeaveFormProject_LeaveRequest.tLeaveRequest"
          isJavaBased="false">
  <Attribute Name="employeeId" IsUpdateable="0" Type="java.lang.String">
    <Properties>
      <CustomProperties>
        <Property Name="nextSiblingNamespace" Value="http://www.example.org"/>
        <Property Name="nextSibling" Value="fullName"/>
        <Property Name="minOccurs" Value="1"/>
        <Property Name="maxOccurs" Value="1"/>
        <Property Name="LABEL" Value="Employee Id"/>
        <Property Name="LeafElement_hint" Value="LeafElement_no_attribute"/>
        <Property Name="nillable" Value="false"/>
        <Property Name="originalName" Value="employeeId"/>
        <Property Name="targetNamespace" Value="http://www.example.org"/>
        <Property Name="type" Value="java.lang.String"/>
      </CustomProperties>
    </Properties>
  </Attribute>
  <Attribute Name="fullName" IsUpdateable="0" Type="java.lang.String">
    <Properties>
      <CustomProperties>
        <Property Name="nextSiblingNamespace" Value="http://www.example.org"/>
        <Property Name="nextSibling" Value="startDate"/>
        <Property Name="minOccurs" Value="1"/>
        <Property Name="maxOccurs" Value="1"/>
        <Property Name="LABEL" Value="Full Name"/>
        <Property Name="LeafElement_hint" Value="LeafElement_no_attribute"/>
        <Property Name="nillable" Value="false"/>
        <Property Name="originalName" Value="fullName"/>
        <Property Name="targetNamespace" Value="http://www.example.org"/>
        <Property Name="type" Value="java.lang.String"/>
      </CustomProperties>
    </Properties>
  </Attribute>
  <Attribute Name="startDate" IsUpdateable="0"
             Type="oracle.bpel.services.datacontrol.types.XSDate">
    <Properties>
      <CustomProperties>
        <Property Name="nextSiblingNamespace" Value="http://www.example.org"/>
        <Property Name="nextSibling" Value="endDate"/>
        <Property Name="minOccurs" Value="1"/>
        <Property Name="maxOccurs" Value="1"/>
        <Property Name="LABEL" Value="Start Date"/>
        <Property Name="LeafElement_hint" Value="LeafElement_no_attribute"/>
        <Property Name="nillable" Value="false"/>
        <Property Name="originalName" Value="startDate"/>
        <Property Name="targetNamespace" Value="http://www.example.org"/>
        <Property Name="type"
                  Value="oracle.bpel.services.datacontrol.types.XSDate"/>
      </CustomProperties>
    </Properties>
  </Attribute>
  <Attribute Name="endDate" IsUpdateable="0"
             Type="oracle.bpel.services.datacontrol.types.XSDate">
    <Properties>
      <CustomProperties>
        <Property Name="nextSiblingNamespace" Value="http://www.example.org"/>
        <Property Name="nextSibling" Value="leaveType"/>
        <Property Name="minOccurs" Value="1"/>
        <Property Name="maxOccurs" Value="1"/>
        <Property Name="LABEL" Value="End Date"/>
        <Property Name="LeafElement_hint" Value="LeafElement_no_attribute"/>
        <Property Name="nillable" Value="false"/>
        <Property Name="originalName" Value="endDate"/>
        <Property Name="targetNamespace" Value="http://www.example.org"/>
        <Property Name="type"
                  Value="oracle.bpel.services.datacontrol.types.XSDate"/>
      </CustomProperties>
    </Properties>
  </Attribute>
  <Attribute Name="leaveType" IsUpdateable="0" Type="java.lang.String">
    <Properties>
      <CustomProperties>
        <Property Name="nextSiblingNamespace" Value="http://www.example.org"/>
        <Property Name="nextSibling" Value="leaveReason"/>
        <Property Name="minOccurs" Value="1"/>
        <Property Name="maxOccurs" Value="1"/>
        <Property Name="LABEL" Value="Leave Type"/>
        <Property Name="LeafElement_hint" Value="LeafElement_no_attribute"/>
        <Property Name="nillable" Value="false"/>
        <Property Name="originalName" Value="leaveType"/>
        <Property Name="targetNamespace" Value="http://www.example.org"/>
        <Property Name="type" Value="java.lang.String"/>
      </CustomProperties>
    </Properties>
  </Attribute>
  <Attribute Name="leaveReason" IsUpdateable="0" Type="java.lang.String">
    <Properties>
      <CustomProperties>
        <Property Name="nextSiblingNamespace" Value="http://www.example.org"/>
        <Property Name="nextSibling" Value="requestStatus"/>
        <Property Name="minOccurs" Value="1"/>
        <Property Name="maxOccurs" Value="1"/>
        <Property Name="LABEL" Value="Leave Reason"/>
        <Property Name="LeafElement_hint" Value="LeafElement_no_attribute"/>
        <Property Name="nillable" Value="false"/>
        <Property Name="originalName" Value="leaveReason"/>
        <Property Name="targetNamespace" Value="http://www.example.org"/>
        <Property Name="type" Value="java.lang.String"/>
      </CustomProperties>
    </Properties>
  </Attribute>
  <Attribute Name="requestStatus" IsUpdateable="0" Type="java.lang.String">
    <Properties>
      <CustomProperties>
        <Property Name="minOccurs" Value="1"/>
        <Property Name="maxOccurs" Value="1"/>
        <Property Name="LABEL" Value="Request Status"/>
        <Property Name="LeafElement_hint" Value="LeafElement_no_attribute"/>
        <Property Name="nillable" Value="false"/>
        <Property Name="originalName" Value="requestStatus"/>
        <Property Name="targetNamespace" Value="http://www.example.org"/>
        <Property Name="type" Value="java.lang.String"/>
      </CustomProperties>
    </Properties>
  </Attribute>
</JavaBean>
